aiogram_newsletter/__init__.py
aiogram_newsletter/handlers.py
aiogram_newsletter/manager.py
aiogram_newsletter/middleware.py
aiogram_newsletter/utils/__init__.py
aiogram_newsletter/utils/exceptions.py
aiogram_newsletter/utils/keyboards.py
aiogram_newsletter/utils/misc.py
aiogram_newsletter/utils/states.py
aiogram_newsletter/utils/texts.py
aiogram_newsletter-0.0.12.dist-info/LICENSE
aiogram_newsletter-0.0.12.dist-info/METADATA
aiogram_newsletter-0.0.12.dist-info/WHEEL
aiogram_newsletter-0.0.12.dist-info/top_level.txt
aiogram_newsletter-0.0.12.dist-info/RECORD
