Metadata-Version: 2.1
Name: aiogram-newsletter
Version: 0.0.12
Summary: Newsletter handler for aiogram bots.
Home-page: https://github.com/nessshon/aiogram-newsletter/
Author: nessshon
Classifier: Programming Language :: Python :: 3.8
Classifier: Programming Language :: Python :: 3.9
Classifier: Programming Language :: Python :: 3.10
Classifier: Programming Language :: Python :: 3.11
Classifier: Programming Language :: Python :: 3.12
Classifier: License :: OSI Approved :: MIT License
Classifier: Operating System :: OS Independent
License-File: LICENSE
Requires-Dist: aiogram >=3
Requires-Dist: apscheduler ==3.10
